Modules/Shift register/shift_register.v
//Implements a shift register of N bits
//4 functions: SR (01), SL(10), Load(00) and Reset(11) with enable

module shift #(parameter N = 5)(

	input clk,
	input enable,
	input right_in,
	input left_in,
	input [N-1:0] loadin,
	input [1:0] working_mode, //FUNCTION IS A RESERVED KEYWORD. Wasted 2 hours to find that out
	output reg [N-1:0] data //NO COMMA AT THE END OR BOOM
);

always @(posedge (clk)) begin

	if (enable == 1) begin

		if (working_mode == 2'd0)

			data <= loadin;

		if (working_mode == 2'b01)

			//Shift right
			//Removes the least significant bit and adds left_in as MSB
			data <= {left_in, data[N-1:1]};

		if (working_mode == 2'b10) 

			//SL
			//Removes MSB and adds a new LSB

			data <= {data[N-2:0], right_in};

		else

			//Reset
			data <= 0;

	end 

	else

		//Disabled
		data <= data;

end

endmodule

Modules/Shift register/tb_files/shift_register_tb.v
`include "shift_register.v"

module tb();

parameter N = 5;

reg clk = 0;
reg enable = 0;
reg right_in = 0;
reg left_in = 0;
reg [N-1:0] loadin = 0; //name goes after the array size
reg [1:0] working_mode = 0;
wire [N-1:0] data;

always #1 clk = ~clk;

//UUT:

shift test (
	.clk(clk),
	.enable(enable),
	.right_in(right_in),
	.left_in(left_in),
	.loadin(loadin),
	.working_mode(working_mode),
	.data(data)
);

initial begin 

$dumpfile("test_output.vcd");
$dumpvars;

#1 $display("Simulation started. Current data: %b", data);
enable = 1;
#1 $display("[ENABLE TEST] Current data: %b", data);
working_mode = 2'd0;
loadin = 'b10011;
#2 $display("[LOAD TEST of 10011] Current data: %b", data);
working_mode = 2'b01;
left_in = 1;
#2 $display("[SR of 1] Current data: %b", data);
#1 $display ("[SR of 1 again] Current data: %b", data);
working_mode=2'b10;
right_in = 0;
#2 $display ("[SL of 0] Current data: %b", data);
right_in = 1;
#2 $display ("[SL of 1] Current data: %b", data);
working_mode = 2'b11;
#2 $display ("[Reset] Current data: %b", data);

$finish;

end

endmodule

Modules/Shift register/tb_files/test_output.vcd
$date
	Mon Feb 14 16:05:13 2022
$end
$version
	Icarus Verilog
$end
$timescale
	1s
$end
$scope module tb $end
$var wire 5 ! data [4:0] $end
$var reg 1 " clk $end
$var reg 1 # enable $end
$var reg 1 $ left_in $end
$var reg 5 % loadin [4:0] $end
$var reg 1 & right_in $end
$var reg 2 ' working_mode [1:0] $end
$scope module test $end
$var wire 1 " clk $end
$var wire 1 # enable $end
$var wire 1 $ left_in $end
$var wire 5 ( loadin [4:0] $end
$var wire 1 & right_in $end
$var wire 2 ) working_mode [1:0] $end
$var reg 5 * data [4:0] $end
$upscope $end
$upscope $end
$enddefinitions $end
#0
$dumpvars
bx *
b0 )
b0 (
b0 '
0&
b0 %
0$
0#
0"
bx !
$end
#1
b0 !
b0 *
1#
1"
#2
b10011 %
b10011 (
0"
#3
b10011 !
b10011 *
1"
#4
0"
1$
b1 '
b1 )
#5
b11001 !
b11001 *
1"
#6
0"
#7
b10010 !
b10010 *
1"
b10 '
b10 )
#8
0"
#9
b101 !
b101 *
1"
1&
#10
0"
#11
b0 !
b0 *
1"
b11 '
b11 )
